controller.sv
// this module takes the inputs of the microwave controller
// power = 0 for HALF and 1 for FULL
// timer is the heat time
// door_status = 0 for OPEN and 1 for closed
// start_button = 0 initially and 1 when pressed
// cancel_button = 0 initially and 1 when pressed
module controller (input clk,
  input power,
  input [6:0] timer,
  input door_status,
  input start_button,
  input cancel_button,
  output reg [6:0] state_display1,
  output reg [6:0] state_display2,
  output reg [6:0] state_display3,
  output reg [6:0] state_display4,
  output reg [6:0] time_display);
  // fill out code
  // TODO :
  // 1. Implement a countdown counter for the timer
  // 2. Monitor door_status and cancel_button (analogous to reset in Lab4)
  // 3. Monitor start_button (analogous to enable in Lab4)
  // 4. state_display consists of 4-alphabets based on the state of the controller. Use 7-segment display representation to display the state.
 
  
  integer state = 0;
  reg power_level;
  reg[1:0] interrupts = 0;
  comb display(
    .state(state),
    .state_display({state_display1, state_display2, state_display3, state_display4})
  );
  
  // the instructions are so unbelievably unclear that i'm just
  // implementing the "allow timer to be set while in PrOC after
  // the door is closed but before the start button is pressed"
  // behavior this way in case it has to be taken out later
  reg door_is_closed_but_still_waiting_for_start_to_be_pressed = 0;
  
  // we only need to asynchronously handle opening the door when the food is done.
  // in any other situation, opening the door has no discernable behavior that can't
  // be handled synchronously
  always @(negedge door_status) begin
      if (state == 2) begin
        /* dOnE state: change display to IdLE */
        state = 0;
      end
  end
  
  // basic 1-level-deep interrupt queue in case these buttons are pressed & released
  // quicker than the clk period 
  always @(posedge cancel_button, posedge start_button) begin
    interrupts[1] |= cancel_button;
    interrupts[0] |= start_button;
  end

  always @(posedge clk) begin
    if (interrupts[1]) begin // cancel button
      interrupts[1] = 0;
      state <= 0;
      time_display = 0;
    end else begin
      if (!state) begin // IdLE
        // check to see if power & timer have been properly set
        // if not, set to default values
        if (power !== 1) begin
          power_level = 0;
        end else begin
          power_level = power;
        end
        if ((timer^timer) !== 7'b0 || timer > 120) begin
          time_display = 60;
        end else begin
          time_display = timer;
        end
        if (interrupts == 2'b01 && door_status) begin // start button
          interrupts[0] = 0;
          state <= 1;
        end
      end else if (state == 1) begin // PrOC
        // time's up!
        // since the timer will take an extra clk cycle for the display change
        // to occur, we want to "stop" it at 1 rather than 0. Then we can just
        // set it to zero at the same time 
        if (time_display == 1) begin
          time_display = 0;
          state <= 2;
        end else begin
          if (!door_status) begin
            wait(door_status);
            door_is_closed_but_still_waiting_for_start_to_be_pressed = 1;
            @(posedge start_button);
            door_is_closed_but_still_waiting_for_start_to_be_pressed = 0;
            interrupts[0] = 0;
          end
          time_display = time_display - 1;
        end
      end
    end
  end
  
  // allow changing the timer while the door is open
  // (no need to set a default value -- if the user enters gibberish
  // just resume where we left off)
  always @(timer) begin
    if (!door_status || door_is_closed_but_still_waiting_for_start_to_be_pressed) begin
      if ((timer^timer) === 7'b0 && timer <= 120) begin
        time_display = timer;
      end
    end
  end
endmodule

module comb(input[31:0] state, output reg[3:0][6:0] state_display);
  // state_display: disp1, disp2, disp3, disp4
  // display format is abcdefg

  // we need to initialize the display right away, and then update
  // whenever a state change occurs
  always_comb begin
    case (state)
      0:  /* IdLE -- BC, BCDEG, DEF, ADEFG */
          state_display = {7'b0110000, 7'b0111101, 7'b0001110, 7'b1001111};
      1:  /* PrOC -- ABEFG, AEF, ABCDEF, ADEF */
          state_display = {7'b1100111, 7'b1000110, 7'b1111110, 7'b1001110};
      2:  /* dOnE -- BCDEG, ABCDEF, CEG, ADEFG */
          state_display = {7'b0111101, 7'b1111110, 7'b0010101, 7'b1001111};
    endcase
  end
endmodule

Lab_06_controller_tb.sv
module controller_tb();

	// declare variables
	parameter CLK = 10;
	reg clk = 0;
	reg power, door_status, start_button, cancel_button;
	reg [6:0] timer ;
	wire [6:0] state_display1; // I or P or d
	wire [6:0] state_display2; // d or r or O
	wire [6:0] state_display3; // L or O or n
	wire [6:0] state_display4; // E or C or E
	wire [6:0] time_display;
	
	initial begin
	forever begin
	clk <= ~clk;
	#5;
	end
	end
	
	controller ctl (. clk(clk),
	.power(power),
	.timer(timer),
	.door_status(door_status),
	.start_button(start_button),
	.cancel_button(cancel_button),
	.state_display1(state_display1),
	.state_display2(state_display2),
	.state_display3(state_display3),
	.state_display4(state_display4),
	.time_display(time_display)
	);
	
	initial begin
	$dumpfile("dump.vcd");
	$dumpvars(0, controller_tb);
	// Possible scenario 1
	// default settings
	power <= 0; // power is HALF
	timer <= 7'b111100 ; // timer is 60s
	door_status <= 0; // Door is open
	start_button <= 0; // start button not pressed
	cancel_button <= 0; // cancel button not pressed
	#CLK //1 clock cycle to place food
	door_status <=1; // Door is closed
	power <= 1; // Power is set to FULL
	timer <= 7'b1100100 ; // timer is set to 100s
	start_button <= 1; // start button pressed
	#5 start_button <= 0; // start button reset at negedge
	#(100*CLK +5) door_status <= 0; // Door opened after 101 s - 1s extra to display dOnE
	#CLK timer <= 7'b111100 ; // timer is reset to 60s
	door_status = 1; // 1 clock cycle to remove food and door is closed
	// write test bench for possible scenarios 2, 3 and 4
	#20

	//SCENARIO TWO
	// default 
	power <= 0; // power is HALF
	timer <= 7'b111100 ; // timer is 60s
	door_status <= 0; // Door is open
	start_button <= 0; // start button not pressed
	cancel_button <= 0; // cancel button not pressed
	// put food in
	#CLK
	door_status <= 1; // door closed
	power <= 0;  // power half
	timer <= 7'b1100100; //set timer to 100 sec
	#CLK
	start_button <= 1; // start
	#5 start_button <= 0; // start button reset at negedge
	#(40*CLK + 5) door_status <= 0; // door opened afer 40 sec? 
	#CLK // remove food
	#CLK // put food back
	door_status = 1; //door closed again
	#CLK
	start_button <= 1; // start
	#5 start_button <= 0; // start button reset at negedge
	#(60*CLK + 5) door_status = 0; // door opened once done
	door_status = 1;
	#20

	//SCENARIO THREE
	// default 
	power <= 0; // power is HALF
	timer <= 7'b0111100 ; // timer is 60s
	door_status <= 0; // Door is open
	start_button <= 0; // start button not pressed
	cancel_button <= 0; // cancel button not pressed
	// put food in
	#CLK
	door_status <= 1; // close door
	power <= 1; //power FULL
	timer <= 7'b1100100; // timer 100 seconds set
	#CLK
	start_button <= 1; // press start button
	#5 start_button <= 0; // start button reset at negedge
	#(30*CLK + 5) door_status <= 0; // wait 30 second and open door
	#CLK // remove food, put it back
	door_status <= 1; // close door again
	#CLK
	//cancel_button <= 1;
	//#5 cancel_button <= 0;
	//#CLK
	timer <= 7'b0110010; // set to 50 seconds 
	#CLK
	start_button <= 1; // press start button
	#5 start_button <= 0; // start button reset at negedge
	#(50*CLK + 5) door_status <= 0; // open door once done
	#CLK // remove food
	door_status <= 1; //close door
	#20

	//SCENARIO FOUR
	// default 
	power <= 0; // power is HALF
	timer <= 7'b0111100 ; // timer is 60s
	door_status <= 0; // Door is open
	start_button <= 0; // start button not pressed
	#5 start_button <= 0; // start button reset at negedge
	cancel_button <= 0; // cancel button not pressed
	// put food in
	#CLK
	door_status <= 1; // door closed
	power <= 1; // power FULL
	timer <= 7'b1100100; // set timer to 100 sec
	#CLK
	start_button <= 1; //press start
	#5 start_button <= 0; // start button reset at negedge
	#(30*CLK + 5) cancel_button <= 1; // press cancel after 30 sec
	#5 cancel_button <= 0; // cancel button reset at negedge
	door_status <= 0; // open door

	$finish;
	end
endmodule

dump.vcd
$date
	Mon May 24 15:53:02 2021
$end
$version
	Icarus Verilog
$end
$timescale
	1s
$end
$scope module controller_tb $end
$var wire 7 ! time_display [6:0] $end
$var wire 7 " state_display4 [6:0] $end
$var wire 7 # state_display3 [6:0] $end
$var wire 7 $ state_display2 [6:0] $end
$var wire 7 % state_display1 [6:0] $end
$var reg 1 & cancel_button $end
$var reg 1 ' clk $end
$var reg 1 ( door_status $end
$var reg 1 ) power $end
$var reg 1 * start_button $end
$var reg 7 + timer [6:0] $end
$scope module ctl $end
$var wire 1 & cancel_button $end
$var wire 1 ' clk $end
$var wire 1 ( door_status $end
$var wire 1 ) power $end
$var wire 1 * start_button $end
$var wire 7 , timer [6:0] $end
$var wire 7 - state_display4 [6:0] $end
$var wire 7 . state_display3 [6:0] $end
$var wire 7 / state_display2 [6:0] $end
$var wire 7 0 state_display1 [6:0] $end
$var reg 1 1 door_is_closed_but_still_waiting_for_start_to_be_pressed $end
$var reg 2 2 interrupts [1:0] $end
$var reg 1 3 power_level $end
$var reg 7 4 time_display [6:0] $end
$var integer 32 5 state [31:0] $end
$scope module display $end
$var wire 32 6 state [31:0] $end
$var reg 28 7 state_display [27:0] $end
$upscope $end
$upscope $end
$upscope $end
$enddefinitions $end
#0
$dumpvars
b110000011110100011101001111 7
b0 6
b0 5
b111100 4
03
b0 2
01
b110000 0
b111101 /
b1110 .
b1001111 -
b111100 ,
b111100 +
0*
0)
0(
1'
0&
b110000 %
b111101 $
b1110 #
b1001111 "
b111100 !
$end
#5
0'
#10
b1001110 "
b1001110 -
b1111110 #
b1111110 .
b1000110 $
b1000110 /
b1100111 %
b1100111 0
b1100111100011011111101001110 7
b1 5
b1 6
b1100100 !
b1100100 4
13
b0 2
1'
1*
b1100100 +
b1100100 ,
1)
1(
#15
0'
0*
#20
b1100011 !
b1100011 4
1'
#25
0'
#30
b1100010 !
b1100010 4
1'
#35
0'
#40
b1100001 !
b1100001 4
1'
#45
0'
#50
b1100000 !
b1100000 4
1'
#55
0'
#60
b1011111 !
b1011111 4
1'
#65
0'
#70
b1011110 !
b1011110 4
1'
#75
0'
#80
b1011101 !
b1011101 4
1'
#85
0'
#90
b1011100 !
b1011100 4
1'
#95
0'
#100
b1011011 !
b1011011 4
1'
#105
0'
#110
b1011010 !
b1011010 4
1'
#115
0'
#120
b1011001 !
b1011001 4
1'
#125
0'
#130
b1011000 !
b1011000 4
1'
#135
0'
#140
b1010111 !
b1010111 4
1'
#145
0'
#150
b1010110 !
b1010110 4
1'
#155
0'
#160
b1010101 !
b1010101 4
1'
#165
0'
#170
b1010100 !
b1010100 4
1'
#175
0'
#180
b1010011 !
b1010011 4
1'
#185
0'
#190
b1010010 !
b1010010 4
1'
#195
0'
#200
b1010001 !
b1010001 4
1'
#205
0'
#210
b1010000 !
b1010000 4
1'
#215
0'
#220
b1001111 !
b1001111 4
1'
#225
0'
#230
b1001110 !
b1001110 4
1'
#235
0'
#240
b1001101 !
b1001101 4
1'
#245
0'
#250
b1001100 !
b1001100 4
1'
#255
0'
#260
b1001011 !
b1001011 4
1'
#265
0'
#270
b1001010 !
b1001010 4
1'
#275
0'
#280
b1001001 !
b1001001 4
1'
#285
0'
#290
b1001000 !
b1001000 4
1'
#295
0'
#300
b1000111 !
b1000111 4
1'
#305
0'
#310
b1000110 !
b1000110 4
1'
#315
0'
#320
b1000101 !
b1000101 4
1'
#325
0'
#330
b1000100 !
b1000100 4
1'
#335
0'
#340
b1000011 !
b1000011 4
1'
#345
0'
#350
b1000010 !
b1000010 4
1'
#355
0'
#360
b1000001 !
b1000001 4
1'
#365
0'
#370
b1000000 !
b1000000 4
1'
#375
0'
#380
b111111 !
b111111 4
1'
#385
0'
#390
b111110 !
b111110 4
1'
#395
0'
#400
b111101 !
b111101 4
1'
#405
0'
#410
b111100 !
b111100 4
1'
#415
0'
#420
b111011 !
b111011 4
1'
#425
0'
#430
b111010 !
b111010 4
1'
#435
0'
#440
b111001 !
b111001 4
1'
#445
0'
#450
b111000 !
b111000 4
1'
#455
0'
#460
b110111 !
b110111 4
1'
#465
0'
#470
b110110 !
b110110 4
1'
#475
0'
#480
b110101 !
b110101 4
1'
#485
0'
#490
b110100 !
b110100 4
1'
#495
0'
#500
b110011 !
b110011 4
1'
#505
0'
#510
b110010 !
b110010 4
1'
#515
0'
#520
b110001 !
b110001 4
1'
#525
0'
#530
b110000 !
b110000 4
1'
#535
0'
#540
b101111 !
b101111 4
1'
#545
0'
#550
b101110 !
b101110 4
1'
#555
0'
#560
b101101 !
b101101 4
1'
#565
0'
#570
b101100 !
b101100 4
1'
#575
0'
#580
b101011 !
b101011 4
1'
#585
0'
#590
b101010 !
b101010 4
1'
#595
0'
#600
b101001 !
b101001 4
1'
#605
0'
#610
b101000 !
b101000 4
1'
#615
0'
#620
b100111 !
b100111 4
1'
#625
0'
#630
b100110 !
b100110 4
1'
#635
0'
#640
b100101 !
b100101 4
1'
#645
0'
#650
b100100 !
b100100 4
1'
#655
0'
#660
b100011 !
b100011 4
1'
#665
0'
#670
b100010 !
b100010 4
1'
#675
0'
#680
b100001 !
b100001 4
1'
#685
0'
#690
b100000 !
b100000 4
1'
#695
0'
#700
b11111 !
b11111 4
1'
#705
0'
#710
b11110 !
b11110 4
1'
#715
0'
#720
b11101 !
b11101 4
1'
#725
0'
#730
b11100 !
b11100 4
1'
#735
0'
#740
b11011 !
b11011 4
1'
#745
0'
#750
b11010 !
b11010 4
1'
#755
0'
#760
b11001 !
b11001 4
1'
#765
0'
#770
b11000 !
b11000 4
1'
#775
0'
#780
b10111 !
b10111 4
1'
#785
0'
#790
b10110 !
b10110 4
1'
#795
0'
#800
b10101 !
b10101 4
1'
#805
0'
#810
b10100 !
b10100 4
1'
#815
0'
#820
b10011 !
b10011 4
1'
#825
0'
#830
b10010 !
b10010 4
1'
#835
0'
#840
b10001 !
b10001 4
1'
#845
0'
#850
b10000 !
b10000 4
1'
#855
0'
#860
b1111 !
b1111 4
1'
#865
0'
#870
b1110 !
b1110 4
1'
#875
0'
#880
b1101 !
b1101 4
1'
#885
0'
#890
b1100 !
b1100 4
1'
#895
0'
#900
b1011 !
b1011 4
1'
#905
0'
#910
b1010 !
b1010 4
1'
#915
0'
#920
b1001 !
b1001 4
1'
#925
0'
#930
b1000 !
b1000 4
1'
#935
0'
#940
b111 !
b111 4
1'
#945
0'
#950
b110 !
b110 4
1'
#955
0'
#960
b101 !
b101 4
1'
#965
0'
#970
b100 !
b100 4
1'
#975
0'
#980
b11 !
b11 4
1'
#985
0'
#990
b10 !
b10 4
1'
#995
0'
#1000
b1 !
b1 4
1'
#1005
0'
#1010
b1001111 "
b1001111 -
b10101 #
b10101 .
b1111110 $
b1111110 /
b111101 %
b111101 0
b111101111111000101011001111 7
b10 5
b10 6
b0 !
b0 4
1'
#1015
0'
#1020
b1110 #
b1110 .
b111101 $
b111101 /
b110000 %
b110000 0
b110000011110100011101001111 7
b1100100 !
b1100100 4
b0 5
b0 6
1'
0(
#1025
0'
#1030
b111100 !
b111100 4
1'
b111100 +
b111100 ,
1(
#1035
0'
#1040
1'
#1045
0'
#1050
03
1'
0(
0)
#1055
0'
#1060
b1100100 !
b1100100 4
1'
b1100100 +
b1100100 ,
1(
#1065
0'
#1070
b1001110 "
b1001110 -
b1111110 #
b1111110 .
b1000110 $
b1000110 /
b1100111 %
b1100111 0
b1100111100011011111101001110 7
b1 5
b1 6
b0 2
1'
1*
#1075
0'
0*
#1080
b1100011 !
b1100011 4
1'
#1085
0'
#1090
b1100010 !
b1100010 4
1'
#1095
0'
#1100
b1100001 !
b1100001 4
1'
#1105
0'
#1110
b1100000 !
b1100000 4
1'
#1115
0'
#1120
b1011111 !
b1011111 4
1'
#1125
0'
#1130
b1011110 !
b1011110 4
1'
#1135
0'
#1140
b1011101 !
b1011101 4
1'
#1145
0'
#1150
b1011100 !
b1011100 4
1'
#1155
0'
#1160
b1011011 !
b1011011 4
1'
#1165
0'
#1170
b1011010 !
b1011010 4
1'
#1175
0'
#1180
b1011001 !
b1011001 4
1'
#1185
0'
#1190
b1011000 !
b1011000 4
1'
#1195
0'
#1200
b1010111 !
b1010111 4
1'
#1205
0'
#1210
b1010110 !
b1010110 4
1'
#1215
0'
#1220
b1010101 !
b1010101 4
1'
#1225
0'
#1230
b1010100 !
b1010100 4
1'
#1235
0'
#1240
b1010011 !
b1010011 4
1'
#1245
0'
#1250
b1010010 !
b1010010 4
1'
#1255
0'
#1260
b1010001 !
b1010001 4
1'
#1265
0'
#1270
b1010000 !
b1010000 4
1'
#1275
0'
#1280
b1001111 !
b1001111 4
1'
#1285
0'
#1290
b1001110 !
b1001110 4
1'
#1295
0'
#1300
b1001101 !
b1001101 4
1'
#1305
0'
#1310
b1001100 !
b1001100 4
1'
#1315
0'
#1320
b1001011 !
b1001011 4
1'
#1325
0'
#1330
b1001010 !
b1001010 4
1'
#1335
0'
#1340
b1001001 !
b1001001 4
1'
#1345
0'
#1350
b1001000 !
b1001000 4
1'
#1355
0'
#1360
b1000111 !
b1000111 4
1'
#1365
0'
#1370
b1000110 !
b1000110 4
1'
#1375
0'
#1380
b1000101 !
b1000101 4
1'
#1385
0'
#1390
b1000100 !
b1000100 4
1'
#1395
0'
#1400
b1000011 !
b1000011 4
1'
#1405
0'
#1410
b1000010 !
b1000010 4
1'
#1415
0'
#1420
b1000001 !
b1000001 4
1'
#1425
0'
#1430
b1000000 !
b1000000 4
1'
#1435
0'
#1440
b111111 !
b111111 4
1'
#1445
0'
#1450
b111110 !
b111110 4
1'
#1455
0'
#1460
b111101 !
b111101 4
1'
#1465
0'
#1470
b111100 !
b111100 4
1'
#1475
0'
#1480
1'
0(
#1485
0'
#1490
1'
#1495
0'
#1500
1'
11
1(
#1505
0'
#1510
b111011 !
b111011 4
01
b0 2
1'
1*
#1515
0'
0*
#1520
b111010 !
b111010 4
1'
#1525
0'
#1530
b111001 !
b111001 4
1'
#1535
0'
#1540
b111000 !
b111000 4
1'
#1545
0'
#1550
b110111 !
b110111 4
1'
#1555
0'
#1560
b110110 !
b110110 4
1'
#1565
0'
#1570
b110101 !
b110101 4
1'
#1575
0'
#1580
b110100 !
b110100 4
1'
#1585
0'
#1590
b110011 !
b110011 4
1'
#1595
0'
#1600
b110010 !
b110010 4
1'
#1605
0'
#1610
b110001 !
b110001 4
1'
#1615
0'
#1620
b110000 !
b110000 4
1'
#1625
0'
#1630
b101111 !
b101111 4
1'
#1635
0'
#1640
b101110 !
b101110 4
1'
#1645
0'
#1650
b101101 !
b101101 4
1'
#1655
0'
#1660
b101100 !
b101100 4
1'
#1665
0'
#1670
b101011 !
b101011 4
1'
#1675
0'
#1680
b101010 !
b101010 4
1'
#1685
0'
#1690
b101001 !
b101001 4
1'
#1695
0'
#1700
b101000 !
b101000 4
1'
#1705
0'
#1710
b100111 !
b100111 4
1'
#1715
0'
#1720
b100110 !
b100110 4
1'
#1725
0'
#1730
b100101 !
b100101 4
1'
#1735
0'
#1740
b100100 !
b100100 4
1'
#1745
0'
#1750
b100011 !
b100011 4
1'
#1755
0'
#1760
b100010 !
b100010 4
1'
#1765
0'
#1770
b100001 !
b100001 4
1'
#1775
0'
#1780
b100000 !
b100000 4
1'
#1785
0'
#1790
b11111 !
b11111 4
1'
#1795
0'
#1800
b11110 !
b11110 4
1'
#1805
0'
#1810
b11101 !
b11101 4
1'
#1815
0'
#1820
b11100 !
b11100 4
1'
#1825
0'
#1830
b11011 !
b11011 4
1'
#1835
0'
#1840
b11010 !
b11010 4
1'
#1845
0'
#1850
b11001 !
b11001 4
1'
#1855
0'
#1860
b11000 !
b11000 4
1'
#1865
0'
#1870
b10111 !
b10111 4
1'
#1875
0'
#1880
b10110 !
b10110 4
1'
#1885
0'
#1890
b10101 !
b10101 4
1'
#1895
0'
#1900
b10100 !
b10100 4
1'
#1905
0'
#1910
b10011 !
b10011 4
1'
#1915
0'
#1920
b10010 !
b10010 4
1'
#1925
0'
#1930
b10001 !
b10001 4
1'
#1935
0'
#1940
b10000 !
b10000 4
1'
#1945
0'
#1950
b1111 !
b1111 4
1'
#1955
0'
#1960
b1110 !
b1110 4
1'
#1965
0'
#1970
b1101 !
b1101 4
1'
#1975
0'
#1980
b1100 !
b1100 4
1'
#1985
0'
#1990
b1011 !
b1011 4
1'
#1995
0'
#2000
b1010 !
b1010 4
1'
#2005
0'
#2010
b1001 !
b1001 4
1'
#2015
0'
#2020
b1000 !
b1000 4
1'
#2025
0'
#2030
b111 !
b111 4
1'
#2035
0'
#2040
b110 !
b110 4
1'
#2045
0'
#2050
b101 !
b101 4
1'
#2055
0'
#2060
b100 !
b100 4
1'
#2065
0'
#2070
b11 !
b11 4
1'
#2075
0'
#2080
b10 !
b10 4
1'
#2085
0'
#2090
b1 !
b1 4
1'
#2095
0'
#2100
b1001111 "
b1001111 -
b10101 #
b10101 .
b1111110 $
b1111110 /
b111101 %
b111101 0
b111101111111000101011001111 7
b10 5
b10 6
b0 !
b0 4
1'
#2105
0'
#2110
1'
#2115
0'
#2120
b1100100 !
b1100100 4
1'
b1110 #
b1110 .
b111101 $
b111101 /
b110000 %
b110000 0
b110000011110100011101001111 7
b0 5
b0 6
1(
#2125
0'
#2130
1'
#2135
0'
#2140
b111100 !
b111100 4
1'
0(
b111100 +
b111100 ,
#2145
0'
#2150
b1100100 !
b1100100 4
13
1'
b1100100 +
b1100100 ,
1)
1(
#2155
0'
#2160
b1001110 "
b1001110 -
b1111110 #
b1111110 .
b1000110 $
b1000110 /
b1100111 %
b1100111 0
b1100111100011011111101001110 7
b1 5
b1 6
b0 2
1'
1*
#2165
0'
0*
#2170
b1100011 !
b1100011 4
1'
#2175
0'
#2180
b1100010 !
b1100010 4
1'
#2185
0'
#2190
b1100001 !
b1100001 4
1'
#2195
0'
#2200
b1100000 !
b1100000 4
1'
#2205
0'
#2210
b1011111 !
b1011111 4
1'
#2215
0'
#2220
b1011110 !
b1011110 4
1'
#2225
0'
#2230
b1011101 !
b1011101 4
1'
#2235
0'
#2240
b1011100 !
b1011100 4
1'
#2245
0'
#2250
b1011011 !
b1011011 4
1'
#2255
0'
#2260
b1011010 !
b1011010 4
1'
#2265
0'
#2270
b1011001 !
b1011001 4
1'
#2275
0'
#2280
b1011000 !
b1011000 4
1'
#2285
0'
#2290
b1010111 !
b1010111 4
1'
#2295
0'
#2300
b1010110 !
b1010110 4
1'
#2305
0'
#2310
b1010101 !
b1010101 4
1'
#2315
0'
#2320
b1010100 !
b1010100 4
1'
#2325
0'
#2330
b1010011 !
b1010011 4
1'
#2335
0'
#2340
b1010010 !
b1010010 4
1'
#2345
0'
#2350
b1010001 !
b1010001 4
1'
#2355
0'
#2360
b1010000 !
b1010000 4
1'
#2365
0'
#2370
b1001111 !
b1001111 4
1'
#2375
0'
#2380
b1001110 !
b1001110 4
1'
#2385
0'
#2390
b1001101 !
b1001101 4
1'
#2395
0'
#2400
b1001100 !
b1001100 4
1'
#2405
0'
#2410
b1001011 !
b1001011 4
1'
#2415
0'
#2420
b1001010 !
b1001010 4
1'
#2425
0'
#2430
b1001001 !
b1001001 4
1'
#2435
0'
#2440
b1001000 !
b1001000 4
1'
#2445
0'
#2450
b1000111 !
b1000111 4
1'
#2455
0'
#2460
b1000110 !
b1000110 4
1'
#2465
0'
#2470
1'
0(
#2475
0'
#2480
11
1'
1(
#2485
0'
#2490
b110010 !
b110010 4
1'
b110010 +
b110010 ,
#2495
0'
#2500
b110001 !
b110001 4
01
b0 2
1'
1*
#2505
0'
0*
#2510
b110000 !
b110000 4
1'
#2515
0'
#2520
b101111 !
b101111 4
1'
#2525
0'
#2530
b101110 !
b101110 4
1'
#2535
0'
#2540
b101101 !
b101101 4
1'
#2545
0'
#2550
b101100 !
b101100 4
1'
#2555
0'
#2560
b101011 !
b101011 4
1'
#2565
0'
#2570
b101010 !
b101010 4
1'
#2575
0'
#2580
b101001 !
b101001 4
1'
#2585
0'
#2590
b101000 !
b101000 4
1'
#2595
0'
#2600
b100111 !
b100111 4
1'
#2605
0'
#2610
b100110 !
b100110 4
1'
#2615
0'
#2620
b100101 !
b100101 4
1'
#2625
0'
#2630
b100100 !
b100100 4
1'
#2635
0'
#2640
b100011 !
b100011 4
1'
#2645
0'
#2650
b100010 !
b100010 4
1'
#2655
0'
#2660
b100001 !
b100001 4
1'
#2665
0'
#2670
b100000 !
b100000 4
1'
#2675
0'
#2680
b11111 !
b11111 4
1'
#2685
0'
#2690
b11110 !
b11110 4
1'
#2695
0'
#2700
b11101 !
b11101 4
1'
#2705
0'
#2710
b11100 !
b11100 4
1'
#2715
0'
#2720
b11011 !
b11011 4
1'
#2725
0'
#2730
b11010 !
b11010 4
1'
#2735
0'
#2740
b11001 !
b11001 4
1'
#2745
0'
#2750
b11000 !
b11000 4
1'
#2755
0'
#2760
b10111 !
b10111 4
1'
#2765
0'
#2770
b10110 !
b10110 4
1'
#2775
0'
#2780
b10101 !
b10101 4
1'
#2785
0'
#2790
b10100 !
b10100 4
1'
#2795
0'
#2800
b10011 !
b10011 4
1'
#2805
0'
#2810
b10010 !
b10010 4
1'
#2815
0'
#2820
b10001 !
b10001 4
1'
#2825
0'
#2830
b10000 !
b10000 4
1'
#2835
0'
#2840
b1111 !
b1111 4
1'
#2845
0'
#2850
b1110 !
b1110 4
1'
#2855
0'
#2860
b1101 !
b1101 4
1'
#2865
0'
#2870
b1100 !
b1100 4
1'
#2875
0'
#2880
b1011 !
b1011 4
1'
#2885
0'
#2890
b1010 !
b1010 4
1'
#2895
0'
#2900
b1001 !
b1001 4
1'
#2905
0'
#2910
b1000 !
b1000 4
1'
#2915
0'
#2920
b111 !
b111 4
1'
#2925
0'
#2930
b110 !
b110 4
1'
#2935
0'
#2940
b101 !
b101 4
1'
#2945
0'
#2950
b100 !
b100 4
1'
#2955
0'
#2960
b11 !
b11 4
1'
#2965
0'
#2970
b10 !
b10 4
1'
#2975
0'
#2980
b1 !
b1 4
1'
#2985
0'
#2990
b1001111 "
b1001111 -
b10101 #
b10101 .
b1111110 $
b1111110 /
b111101 %
b111101 0
b111101111111000101011001111 7
b10 5
b10 6
b0 !
b0 4
1'
#2995
0'
#3000
1'
#3005
0'
#3010
b1110 #
b1110 .
b111101 $
b111101 /
b110000 %
b110000 0
b110000011110100011101001111 7
b110010 !
b110010 4
b0 5
b0 6
1'
0(
#3015
0'
#3020
1'
1(
#3025
0'
#3030
1'
#3035
0'
#3040
03
b111100 !
b111100 4
1'
0(
b111100 +
b111100 ,
0)
#3045
0'
#3050
1'
#3055
0'
b1100100 +
b1100100 ,
1)
1(
#3060
b1100100 !
b1100100 4
13
1'
#3065
b1 2
0'
1*
#3070
b1001110 "
b1001110 -
b1111110 #
b1111110 .
b1000110 $
b1000110 /
b1100111 %
b1100111 0
b1100111100011011111101001110 7
b1 5
b1 6
b0 2
1'
0*
#3075
0'
#3080
b1100011 !
b1100011 4
1'
#3085
0'
#3090
b1100010 !
b1100010 4
1'
#3095
0'
#3100
b1100001 !
b1100001 4
1'
#3105
0'
#3110
b1100000 !
b1100000 4
1'
#3115
0'
#3120
b1011111 !
b1011111 4
1'
#3125
0'
#3130
b1011110 !
b1011110 4
1'
#3135
0'
#3140
b1011101 !
b1011101 4
1'
#3145
0'
#3150
b1011100 !
b1011100 4
1'
#3155
0'
#3160
b1011011 !
b1011011 4
1'
#3165
0'
#3170
b1011010 !
b1011010 4
1'
#3175
0'
#3180
b1011001 !
b1011001 4
1'
#3185
0'
#3190
b1011000 !
b1011000 4
1'
#3195
0'
#3200
b1010111 !
b1010111 4
1'
#3205
0'
#3210
b1010110 !
b1010110 4
1'
#3215
0'
#3220
b1010101 !
b1010101 4
1'
#3225
0'
#3230
b1010100 !
b1010100 4
1'
#3235
0'
#3240
b1010011 !
b1010011 4
1'
#3245
0'
#3250
b1010010 !
b1010010 4
1'
#3255
0'
#3260
b1010001 !
b1010001 4
1'
#3265
0'
#3270
b1010000 !
b1010000 4
1'
#3275
0'
#3280
b1001111 !
b1001111 4
1'
#3285
0'
#3290
b1001110 !
b1001110 4
1'
#3295
0'
#3300
b1001101 !
b1001101 4
1'
#3305
0'
#3310
b1001100 !
b1001100 4
1'
#3315
0'
#3320
b1001011 !
b1001011 4
1'
#3325
0'
#3330
b1001010 !
b1001010 4
1'
#3335
0'
#3340
b1001001 !
b1001001 4
1'
#3345
0'
#3350
b1001000 !
b1001000 4
1'
#3355
0'
#3360
b1000111 !
b1000111 4
1'
#3365
0'
#3370
b1000110 !
b1000110 4
1'
#3375
b10 2
0'
1&
#3380
b1001111 "
b1001111 -
b1110 #
b1110 .
b111101 $
b111101 /
b110000 %
b110000 0
b110000011110100011101001111 7
b0 5
b0 6
b0 !
b0 4
b0 2
1'
0(
0&
